odsl/__init__.py
odsl/__version__.py
odsl/cache.py
odsl/sdk.py
odsl-1.0.10.dist-info/LICENSE
odsl-1.0.10.dist-info/METADATA
odsl-1.0.10.dist-info/WHEEL
odsl-1.0.10.dist-info/top_level.txt
odsl-1.0.10.dist-info/RECORD
