Metadata-Version: 2.1
Name: odsl
Version: 1.0.10
Summary: Python SDK for OpenDataDSL
License: 
Project-URL: Homepage, https://opendatadsl.com
Keywords: OpenDataDSL,ODSL
Requires-Python: >=3.9
License-File: LICENSE
Requires-Dist: requests >=2.31.0
Requires-Dist: msal >=1.26.0
